codec_bridge/__init__.py
codec_bridge/encoding_translator.py
codec_bridge/repository/__init__.py
codec_bridge/repository/python_to_duckdb.py
codec_bridge-0.2.5.dist-info/licenses/license.txt
tests/__init__.py
tests/duckdb_utils.py
tests/generate_test_data.py
codec_bridge-0.2.5.dist-info/METADATA
codec_bridge-0.2.5.dist-info/WHEEL
codec_bridge-0.2.5.dist-info/top_level.txt
codec_bridge-0.2.5.dist-info/RECORD
