Metadata-Version: 2.4
Name: codec_bridge
Version: 0.2.5
Summary: Detect encoding from CSV files and return the accepted case format for analytical tools (currently supports DuckDB)
Home-page: https://github.com/jpferraz-git/codec_bridge
Author: João Pedro Ferraz Bezerra
Author-email: João Pedro Ferraz Bezerra <jpferraz554@gmail.com>
License: MIT License
Classifier: Programming Language :: Python :: 3.12
Classifier: Operating System :: OS Independent
Classifier: Operating System :: Microsoft :: Windows
Classifier: Operating System :: POSIX :: Linux
Requires-Python: >=3.11
License-File: license.txt
Requires-Dist: charset-normalizer>=3.4.2
Requires-Dist: duckdb>=1.3.2
Dynamic: author
Dynamic: home-page
Dynamic: license-file
Dynamic: requires-python
